[
  {
    "surahNo": 51,
    "ayahID": 31,
    "tefsirText": "Daha önce nâzil olan Hûd ve Hicr sûrelerinde, Hz. İbrâhim’e insan kılığında meleklerin  gelmesi, kendisi ve hanımı çok yaşlı oldukları halde, onlara bir oğul müjdelemeleri, ardından da Hz. Lût’un kavmini cezalandırmak üzere gönderildiklerini açıklamaları olayı; yine bu sûrelerde  ve A‘râf sûresinde Lût kavminin  acı âkıbeti anlatılmıştı (bk. A‘râf 7/80-84; Hûd 11/69-83; Hicr 15/51-77). Bu âyetlerde bazı detay farklarıyla aynı konuya yer verilmesi,  38-40.  âyetlerde Firavun ve adamlarının, 41-46. âyetlerde de başka bazı kavimlerin başına gelenlere kısa kısa değinilmesi, bir taraftan gösterilen açık kanıtlara rağmen taşkınlıklarını ve müslümanlara eziyetlerini  gittikçe arttıran müşrikler için bir uyarı, diğer taraftan da Resûl-i  Ekrem ve ona gönülden  bağlanan müminler için bir teselli anlamı taşımaktadır. Burada kıssanın misafir ağırlama bölümü, Allah Teâlâ’nın umulmadık bir anda ve biçimde, dilediği kullarını sıkıntıdan kurtarabileceğinin, bağnaz inkârcıları  da kötü âkıbete çarptırabileceğinin anlaşılmasına ışık tutmaktadır (Râzî, XXVIII, 210). Kur’an’ın bir kıssaya “Sana ulaştı mı?” şeklinde bir soruyla başlaması, o olayın önemine dikkat çektiğini ve Resûlullah’ın  onu ancak vahiy yoluyla bilebildiğini gösteren bir anlatım üslûbudur (Zemahşerî, IV, 28; İbn Âşûr, XXVI, 357). Misafirlerin  melek oluşu ve kelimenin  kök anlamları dikkate alınarak 24. âyette geçen mükremîn kelimesi  “değerli” diye çevrilmiştir. Bu kelimenin “ikram edilenler” anlamını esas alan müfessirler bununla, bizzat Hz. İbrâhim  ve eşinin misafirlere ikramda bulunup hizmet ettiklerine işaret edildiğini belirtirler (Taberî, XXVI, 207); fakat Allah Teâlâ katında ikrama mazhar oldukları için böyle nitelenmiş de olabilirler (İbn Atıyye, V, 177). 25. âyetin “(İçinden) ‘bunlar hiç de tanıdık kimseler değil’ demişti” diye tercüme edilen kısmı “(Onlara) ‘sizi tanımıyoruz, yabancısınız herhalde?’  demişti”  şeklinde  de anlaşılmıştır  (başka yorumlarla birlikte bk. Taberî, XXVI, 208; Zemahşerî, IV, 29-30). 26. âyette kullanılan  râğa fiili  daha çok, “sözünü bitirir  bitirmez, etrafındakilere belli etmeden bulunduğu yerden acele ayrılma”yı ifade eder (İbn Atıyye, V, 177). Olayın akışı dikkate alındığında Hz. İbrâhim farkına varılmayacak şekilde oradan ayrılması değil, gidiş sebebini belli etmeden yani onlara ikram hazırlığı gerekçesini açıklamadan müsaade almış olması muhtemeldir. Bu sebeple meâlde “belli etmeden ... gitti” denmiştir. Hûd sûresinin 69. âyetinde belirtildiği üzere, getirdiği buzağı kızartılmıştı. 27 ve 28. âyetlerde elçilerin yemeğe el sürmemeleri  sebebiyle Hz. İbrâhim’in endişelenmeye başladığı belirtilmektedir. Hûd sûresinin 70. âyetinde bu husus daha açık biçimde  ifade edilmiştir. Bu sebeple müfessirlerin bir kısmı, “Buyurmaz mısınız?” diye çevrilen cümleyi de onların yemediklerini  farketmesi üzerine söylediğini düşünmüşler ve “Niçin yemiyorsunuz ki?” şeklinde anlamışlardır. Kitâb-ı Mukaddes’te ise onların kendileri için hazırlanan yemeği yedikleri yazılıdır (bk. Tekvin, 18/8). Geleneğe göre misafirin kendisine ikram edilen yemeği yememesi hasmâne düşünceler taşıdığının işareti sayılıyordu. Bazı müfessirler Hz.İbrâhim’in endişesinin bu sebebe dayandığı kanaatindedir (İbn Atıyye, V, 178); İbn Abbas’tan gelen bir rivayete göre ise Hz. İbrâhim’in endişesi onların melek olduğunu sezmiş ve azap ile görevli olarak geldiklerini düşünmüş olmasından kaynaklanmıştı (Zemahşerî, IV, 30). 29. âyette Hz. İbrâhim’in eşinin  verilen haber (çocuk müjdesi) karşısındaki tepkisi tasvir edilirken kullanılan kelimelerle ilgili değişik açıklamalar yapılmıştır; bunlar, şaşkınlığını ifade eden bir ses çıkarması ve mahcubiyet içinde yahut hayretinden dolayı elleriyle yüzünü kapatmaya çalışması veya yüzüne vurması şeklinde özetlenebilir. Âyetin “heyecanla bağırarak” diye çevrilen kısmına, “Nazik bir edâ ile oraya geldi, yaklaştı” mânasını verenler de olmuştur (Zemahşerî, IV, 30; İbn Atıyye, V, 178; Şevkânî, V, 102). Lafzan “Yaşlı ve kısır bir kadın!” anlamına gelen hayret ifadesinin ögeleri iki türlü tamamlanarak açıklanmıştır: a) “Ben yaşlı ve kısır bir kadınım!”, b) “Yaşlı ve kısır bir kadın nasıl doğurabilir ki!” (İbn Atıyye, V, 178).  Bir kısım müfessirler bu âyetlerdeki anlatım tarzıyla, misafire hemen geliş sebebini sormayıp önce ikramda bulunma, ikram hazırlığını belli etmeden yapma, olabildiğince en iyi ikramda bulunma, nezaketle buyur etme gibi misafir ağırlama âdâbı ile ilgili bazı kurallara  işaret edildiği kanaatine ulaşmışlardır (Zemahşerî, IV, 30; Râzî, XXVIII, 213-214).  35-37. âyetler meleklerin  Hz. İbrâhim’le konuşmalarının devamı olmayıp burada olayla ilgili ek bir bilgi verilmektedir. 35. âyetin başında yer alan ve meâlde “derken” şeklinde karşılık verdiğimiz “fâ” harfi, meleklerin  Hz. İbrâhim’le  yapılan konuşmadan sonra burada belirtilen noktaya kadar geçen ve Hûd sûresinde anlatılan gelişmelere gönderme yapma anlamı içerir (İbn Âşûr, XXVII, 7)."
  },
  {
    "surahNo": 51,
    "ayahID": 32,
    "tefsirText": "Daha önce nâzil olan Hûd ve Hicr sûrelerinde, Hz. İbrâhim’e insan kılığında meleklerin  gelmesi, kendisi ve hanımı çok yaşlı oldukları halde, onlara bir oğul müjdelemeleri, ardından da Hz. Lût’un kavmini cezalandırmak üzere gönderildiklerini açıklamaları olayı; yine bu sûrelerde  ve A‘râf sûresinde Lût kavminin  acı âkıbeti anlatılmıştı (bk. A‘râf 7/80-84; Hûd 11/69-83; Hicr 15/51-77). Bu âyetlerde bazı detay farklarıyla aynı konuya yer verilmesi,  38-40.  âyetlerde Firavun ve adamlarının, 41-46. âyetlerde de başka bazı kavimlerin başına gelenlere kısa kısa değinilmesi, bir taraftan gösterilen açık kanıtlara rağmen taşkınlıklarını ve müslümanlara eziyetlerini  gittikçe arttıran müşrikler için bir uyarı, diğer taraftan da Resûl-i  Ekrem ve ona gönülden  bağlanan müminler için bir teselli anlamı taşımaktadır. Burada kıssanın misafir ağırlama bölümü, Allah Teâlâ’nın umulmadık bir anda ve biçimde, dilediği kullarını sıkıntıdan kurtarabileceğinin, bağnaz inkârcıları  da kötü âkıbete çarptırabileceğinin anlaşılmasına ışık tutmaktadır (Râzî, XXVIII, 210). Kur’an’ın bir kıssaya “Sana ulaştı mı?” şeklinde bir soruyla başlaması, o olayın önemine dikkat çektiğini ve Resûlullah’ın  onu ancak vahiy yoluyla bilebildiğini gösteren bir anlatım üslûbudur (Zemahşerî, IV, 28; İbn Âşûr, XXVI, 357). Misafirlerin  melek oluşu ve kelimenin  kök anlamları dikkate alınarak 24. âyette geçen mükremîn kelimesi  “değerli” diye çevrilmiştir. Bu kelimenin “ikram edilenler” anlamını esas alan müfessirler bununla, bizzat Hz. İbrâhim  ve eşinin misafirlere ikramda bulunup hizmet ettiklerine işaret edildiğini belirtirler (Taberî, XXVI, 207); fakat Allah Teâlâ katında ikrama mazhar oldukları için böyle nitelenmiş de olabilirler (İbn Atıyye, V, 177). 25. âyetin “(İçinden) ‘bunlar hiç de tanıdık kimseler değil’ demişti” diye tercüme edilen kısmı “(Onlara) ‘sizi tanımıyoruz, yabancısınız herhalde?’  demişti”  şeklinde  de anlaşılmıştır  (başka yorumlarla birlikte bk. Taberî, XXVI, 208; Zemahşerî, IV, 29-30). 26. âyette kullanılan  râğa fiili  daha çok, “sözünü bitirir  bitirmez, etrafındakilere belli etmeden bulunduğu yerden acele ayrılma”yı ifade eder (İbn Atıyye, V, 177). Olayın akışı dikkate alındığında Hz. İbrâhim farkına varılmayacak şekilde oradan ayrılması değil, gidiş sebebini belli etmeden yani onlara ikram hazırlığı gerekçesini açıklamadan müsaade almış olması muhtemeldir. Bu sebeple meâlde “belli etmeden ... gitti” denmiştir. Hûd sûresinin 69. âyetinde belirtildiği üzere, getirdiği buzağı kızartılmıştı. 27 ve 28. âyetlerde elçilerin yemeğe el sürmemeleri  sebebiyle Hz. İbrâhim’in endişelenmeye başladığı belirtilmektedir. Hûd sûresinin 70. âyetinde bu husus daha açık biçimde  ifade edilmiştir. Bu sebeple müfessirlerin bir kısmı, “Buyurmaz mısınız?” diye çevrilen cümleyi de onların yemediklerini  farketmesi üzerine söylediğini düşünmüşler ve “Niçin yemiyorsunuz ki?” şeklinde anlamışlardır. Kitâb-ı Mukaddes’te ise onların kendileri için hazırlanan yemeği yedikleri yazılıdır (bk. Tekvin, 18/8). Geleneğe göre misafirin kendisine ikram edilen yemeği yememesi hasmâne düşünceler taşıdığının işareti sayılıyordu. Bazı müfessirler Hz.İbrâhim’in endişesinin bu sebebe dayandığı kanaatindedir (İbn Atıyye, V, 178); İbn Abbas’tan gelen bir rivayete göre ise Hz. İbrâhim’in endişesi onların melek olduğunu sezmiş ve azap ile görevli olarak geldiklerini düşünmüş olmasından kaynaklanmıştı (Zemahşerî, IV, 30). 29. âyette Hz. İbrâhim’in eşinin  verilen haber (çocuk müjdesi) karşısındaki tepkisi tasvir edilirken kullanılan kelimelerle ilgili değişik açıklamalar yapılmıştır; bunlar, şaşkınlığını ifade eden bir ses çıkarması ve mahcubiyet içinde yahut hayretinden dolayı elleriyle yüzünü kapatmaya çalışması veya yüzüne vurması şeklinde özetlenebilir. Âyetin “heyecanla bağırarak” diye çevrilen kısmına, “Nazik bir edâ ile oraya geldi, yaklaştı” mânasını verenler de olmuştur (Zemahşerî, IV, 30; İbn Atıyye, V, 178; Şevkânî, V, 102). Lafzan “Yaşlı ve kısır bir kadın!” anlamına gelen hayret ifadesinin ögeleri iki türlü tamamlanarak açıklanmıştır: a) “Ben yaşlı ve kısır bir kadınım!”, b) “Yaşlı ve kısır bir kadın nasıl doğurabilir ki!” (İbn Atıyye, V, 178).  Bir kısım müfessirler bu âyetlerdeki anlatım tarzıyla, misafire hemen geliş sebebini sormayıp önce ikramda bulunma, ikram hazırlığını belli etmeden yapma, olabildiğince en iyi ikramda bulunma, nezaketle buyur etme gibi misafir ağırlama âdâbı ile ilgili bazı kurallara  işaret edildiği kanaatine ulaşmışlardır (Zemahşerî, IV, 30; Râzî, XXVIII, 213-214).  35-37. âyetler meleklerin  Hz. İbrâhim’le konuşmalarının devamı olmayıp burada olayla ilgili ek bir bilgi verilmektedir. 35. âyetin başında yer alan ve meâlde “derken” şeklinde karşılık verdiğimiz “fâ” harfi, meleklerin  Hz. İbrâhim’le  yapılan konuşmadan sonra burada belirtilen noktaya kadar geçen ve Hûd sûresinde anlatılan gelişmelere gönderme yapma anlamı içerir (İbn Âşûr, XXVII, 7)."
  },
  {
    "surahNo": 51,
    "ayahID": 33,
    "tefsirText": "Daha önce nâzil olan Hûd ve Hicr sûrelerinde, Hz. İbrâhim’e insan kılığında meleklerin  gelmesi, kendisi ve hanımı çok yaşlı oldukları halde, onlara bir oğul müjdelemeleri, ardından da Hz. Lût’un kavmini cezalandırmak üzere gönderildiklerini açıklamaları olayı; yine bu sûrelerde  ve A‘râf sûresinde Lût kavminin  acı âkıbeti anlatılmıştı (bk. A‘râf 7/80-84; Hûd 11/69-83; Hicr 15/51-77). Bu âyetlerde bazı detay farklarıyla aynı konuya yer verilmesi,  38-40.  âyetlerde Firavun ve adamlarının, 41-46. âyetlerde de başka bazı kavimlerin başına gelenlere kısa kısa değinilmesi, bir taraftan gösterilen açık kanıtlara rağmen taşkınlıklarını ve müslümanlara eziyetlerini  gittikçe arttıran müşrikler için bir uyarı, diğer taraftan da Resûl-i  Ekrem ve ona gönülden  bağlanan müminler için bir teselli anlamı taşımaktadır. Burada kıssanın misafir ağırlama bölümü, Allah Teâlâ’nın umulmadık bir anda ve biçimde, dilediği kullarını sıkıntıdan kurtarabileceğinin, bağnaz inkârcıları  da kötü âkıbete çarptırabileceğinin anlaşılmasına ışık tutmaktadır (Râzî, XXVIII, 210). Kur’an’ın bir kıssaya “Sana ulaştı mı?” şeklinde bir soruyla başlaması, o olayın önemine dikkat çektiğini ve Resûlullah’ın  onu ancak vahiy yoluyla bilebildiğini gösteren bir anlatım üslûbudur (Zemahşerî, IV, 28; İbn Âşûr, XXVI, 357). Misafirlerin  melek oluşu ve kelimenin  kök anlamları dikkate alınarak 24. âyette geçen mükremîn kelimesi  “değerli” diye çevrilmiştir. Bu kelimenin “ikram edilenler” anlamını esas alan müfessirler bununla, bizzat Hz. İbrâhim  ve eşinin misafirlere ikramda bulunup hizmet ettiklerine işaret edildiğini belirtirler (Taberî, XXVI, 207); fakat Allah Teâlâ katında ikrama mazhar oldukları için böyle nitelenmiş de olabilirler (İbn Atıyye, V, 177). 25. âyetin “(İçinden) ‘bunlar hiç de tanıdık kimseler değil’ demişti” diye tercüme edilen kısmı “(Onlara) ‘sizi tanımıyoruz, yabancısınız herhalde?’  demişti”  şeklinde  de anlaşılmıştır  (başka yorumlarla birlikte bk. Taberî, XXVI, 208; Zemahşerî, IV, 29-30). 26. âyette kullanılan  râğa fiili  daha çok, “sözünü bitirir  bitirmez, etrafındakilere belli etmeden bulunduğu yerden acele ayrılma”yı ifade eder (İbn Atıyye, V, 177). Olayın akışı dikkate alındığında Hz. İbrâhim farkına varılmayacak şekilde oradan ayrılması değil, gidiş sebebini belli etmeden yani onlara ikram hazırlığı gerekçesini açıklamadan müsaade almış olması muhtemeldir. Bu sebeple meâlde “belli etmeden ... gitti” denmiştir. Hûd sûresinin 69. âyetinde belirtildiği üzere, getirdiği buzağı kızartılmıştı. 27 ve 28. âyetlerde elçilerin yemeğe el sürmemeleri  sebebiyle Hz. İbrâhim’in endişelenmeye başladığı belirtilmektedir. Hûd sûresinin 70. âyetinde bu husus daha açık biçimde  ifade edilmiştir. Bu sebeple müfessirlerin bir kısmı, “Buyurmaz mısınız?” diye çevrilen cümleyi de onların yemediklerini  farketmesi üzerine söylediğini düşünmüşler ve “Niçin yemiyorsunuz ki?” şeklinde anlamışlardır. Kitâb-ı Mukaddes’te ise onların kendileri için hazırlanan yemeği yedikleri yazılıdır (bk. Tekvin, 18/8). Geleneğe göre misafirin kendisine ikram edilen yemeği yememesi hasmâne düşünceler taşıdığının işareti sayılıyordu. Bazı müfessirler Hz.İbrâhim’in endişesinin bu sebebe dayandığı kanaatindedir (İbn Atıyye, V, 178); İbn Abbas’tan gelen bir rivayete göre ise Hz. İbrâhim’in endişesi onların melek olduğunu sezmiş ve azap ile görevli olarak geldiklerini düşünmüş olmasından kaynaklanmıştı (Zemahşerî, IV, 30). 29. âyette Hz. İbrâhim’in eşinin  verilen haber (çocuk müjdesi) karşısındaki tepkisi tasvir edilirken kullanılan kelimelerle ilgili değişik açıklamalar yapılmıştır; bunlar, şaşkınlığını ifade eden bir ses çıkarması ve mahcubiyet içinde yahut hayretinden dolayı elleriyle yüzünü kapatmaya çalışması veya yüzüne vurması şeklinde özetlenebilir. Âyetin “heyecanla bağırarak” diye çevrilen kısmına, “Nazik bir edâ ile oraya geldi, yaklaştı” mânasını verenler de olmuştur (Zemahşerî, IV, 30; İbn Atıyye, V, 178; Şevkânî, V, 102). Lafzan “Yaşlı ve kısır bir kadın!” anlamına gelen hayret ifadesinin ögeleri iki türlü tamamlanarak açıklanmıştır: a) “Ben yaşlı ve kısır bir kadınım!”, b) “Yaşlı ve kısır bir kadın nasıl doğurabilir ki!” (İbn Atıyye, V, 178).  Bir kısım müfessirler bu âyetlerdeki anlatım tarzıyla, misafire hemen geliş sebebini sormayıp önce ikramda bulunma, ikram hazırlığını belli etmeden yapma, olabildiğince en iyi ikramda bulunma, nezaketle buyur etme gibi misafir ağırlama âdâbı ile ilgili bazı kurallara  işaret edildiği kanaatine ulaşmışlardır (Zemahşerî, IV, 30; Râzî, XXVIII, 213-214).  35-37. âyetler meleklerin  Hz. İbrâhim’le konuşmalarının devamı olmayıp burada olayla ilgili ek bir bilgi verilmektedir. 35. âyetin başında yer alan ve meâlde “derken” şeklinde karşılık verdiğimiz “fâ” harfi, meleklerin  Hz. İbrâhim’le  yapılan konuşmadan sonra burada belirtilen noktaya kadar geçen ve Hûd sûresinde anlatılan gelişmelere gönderme yapma anlamı içerir (İbn Âşûr, XXVII, 7)."
  },
  {
    "surahNo": 51,
    "ayahID": 34,
    "tefsirText": "Daha önce nâzil olan Hûd ve Hicr sûrelerinde, Hz. İbrâhim’e insan kılığında meleklerin  gelmesi, kendisi ve hanımı çok yaşlı oldukları halde, onlara bir oğul müjdelemeleri, ardından da Hz. Lût’un kavmini cezalandırmak üzere gönderildiklerini açıklamaları olayı; yine bu sûrelerde  ve A‘râf sûresinde Lût kavminin  acı âkıbeti anlatılmıştı (bk. A‘râf 7/80-84; Hûd 11/69-83; Hicr 15/51-77). Bu âyetlerde bazı detay farklarıyla aynı konuya yer verilmesi,  38-40.  âyetlerde Firavun ve adamlarının, 41-46. âyetlerde de başka bazı kavimlerin başına gelenlere kısa kısa değinilmesi, bir taraftan gösterilen açık kanıtlara rağmen taşkınlıklarını ve müslümanlara eziyetlerini  gittikçe arttıran müşrikler için bir uyarı, diğer taraftan da Resûl-i  Ekrem ve ona gönülden  bağlanan müminler için bir teselli anlamı taşımaktadır. Burada kıssanın misafir ağırlama bölümü, Allah Teâlâ’nın umulmadık bir anda ve biçimde, dilediği kullarını sıkıntıdan kurtarabileceğinin, bağnaz inkârcıları  da kötü âkıbete çarptırabileceğinin anlaşılmasına ışık tutmaktadır (Râzî, XXVIII, 210). Kur’an’ın bir kıssaya “Sana ulaştı mı?” şeklinde bir soruyla başlaması, o olayın önemine dikkat çektiğini ve Resûlullah’ın  onu ancak vahiy yoluyla bilebildiğini gösteren bir anlatım üslûbudur (Zemahşerî, IV, 28; İbn Âşûr, XXVI, 357). Misafirlerin  melek oluşu ve kelimenin  kök anlamları dikkate alınarak 24. âyette geçen mükremîn kelimesi  “değerli” diye çevrilmiştir. Bu kelimenin “ikram edilenler” anlamını esas alan müfessirler bununla, bizzat Hz. İbrâhim  ve eşinin misafirlere ikramda bulunup hizmet ettiklerine işaret edildiğini belirtirler (Taberî, XXVI, 207); fakat Allah Teâlâ katında ikrama mazhar oldukları için böyle nitelenmiş de olabilirler (İbn Atıyye, V, 177). 25. âyetin “(İçinden) ‘bunlar hiç de tanıdık kimseler değil’ demişti” diye tercüme edilen kısmı “(Onlara) ‘sizi tanımıyoruz, yabancısınız herhalde?’  demişti”  şeklinde  de anlaşılmıştır  (başka yorumlarla birlikte bk. Taberî, XXVI, 208; Zemahşerî, IV, 29-30). 26. âyette kullanılan  râğa fiili  daha çok, “sözünü bitirir  bitirmez, etrafındakilere belli etmeden bulunduğu yerden acele ayrılma”yı ifade eder (İbn Atıyye, V, 177). Olayın akışı dikkate alındığında Hz. İbrâhim farkına varılmayacak şekilde oradan ayrılması değil, gidiş sebebini belli etmeden yani onlara ikram hazırlığı gerekçesini açıklamadan müsaade almış olması muhtemeldir. Bu sebeple meâlde “belli etmeden ... gitti” denmiştir. Hûd sûresinin 69. âyetinde belirtildiği üzere, getirdiği buzağı kızartılmıştı. 27 ve 28. âyetlerde elçilerin yemeğe el sürmemeleri  sebebiyle Hz. İbrâhim’in endişelenmeye başladığı belirtilmektedir. Hûd sûresinin 70. âyetinde bu husus daha açık biçimde  ifade edilmiştir. Bu sebeple müfessirlerin bir kısmı, “Buyurmaz mısınız?” diye çevrilen cümleyi de onların yemediklerini  farketmesi üzerine söylediğini düşünmüşler ve “Niçin yemiyorsunuz ki?” şeklinde anlamışlardır. Kitâb-ı Mukaddes’te ise onların kendileri için hazırlanan yemeği yedikleri yazılıdır (bk. Tekvin, 18/8). Geleneğe göre misafirin kendisine ikram edilen yemeği yememesi hasmâne düşünceler taşıdığının işareti sayılıyordu. Bazı müfessirler Hz.İbrâhim’in endişesinin bu sebebe dayandığı kanaatindedir (İbn Atıyye, V, 178); İbn Abbas’tan gelen bir rivayete göre ise Hz. İbrâhim’in endişesi onların melek olduğunu sezmiş ve azap ile görevli olarak geldiklerini düşünmüş olmasından kaynaklanmıştı (Zemahşerî, IV, 30). 29. âyette Hz. İbrâhim’in eşinin  verilen haber (çocuk müjdesi) karşısındaki tepkisi tasvir edilirken kullanılan kelimelerle ilgili değişik açıklamalar yapılmıştır; bunlar, şaşkınlığını ifade eden bir ses çıkarması ve mahcubiyet içinde yahut hayretinden dolayı elleriyle yüzünü kapatmaya çalışması veya yüzüne vurması şeklinde özetlenebilir. Âyetin “heyecanla bağırarak” diye çevrilen kısmına, “Nazik bir edâ ile oraya geldi, yaklaştı” mânasını verenler de olmuştur (Zemahşerî, IV, 30; İbn Atıyye, V, 178; Şevkânî, V, 102). Lafzan “Yaşlı ve kısır bir kadın!” anlamına gelen hayret ifadesinin ögeleri iki türlü tamamlanarak açıklanmıştır: a) “Ben yaşlı ve kısır bir kadınım!”, b) “Yaşlı ve kısır bir kadın nasıl doğurabilir ki!” (İbn Atıyye, V, 178).  Bir kısım müfessirler bu âyetlerdeki anlatım tarzıyla, misafire hemen geliş sebebini sormayıp önce ikramda bulunma, ikram hazırlığını belli etmeden yapma, olabildiğince en iyi ikramda bulunma, nezaketle buyur etme gibi misafir ağırlama âdâbı ile ilgili bazı kurallara  işaret edildiği kanaatine ulaşmışlardır (Zemahşerî, IV, 30; Râzî, XXVIII, 213-214).  35-37. âyetler meleklerin  Hz. İbrâhim’le konuşmalarının devamı olmayıp burada olayla ilgili ek bir bilgi verilmektedir. 35. âyetin başında yer alan ve meâlde “derken” şeklinde karşılık verdiğimiz “fâ” harfi, meleklerin  Hz. İbrâhim’le  yapılan konuşmadan sonra burada belirtilen noktaya kadar geçen ve Hûd sûresinde anlatılan gelişmelere gönderme yapma anlamı içerir (İbn Âşûr, XXVII, 7)."
  },
  {
    "surahNo": 51,
    "ayahID": 35,
    "tefsirText": "Daha önce nâzil olan Hûd ve Hicr sûrelerinde, Hz. İbrâhim’e insan kılığında meleklerin  gelmesi, kendisi ve hanımı çok yaşlı oldukları halde, onlara bir oğul müjdelemeleri, ardından da Hz. Lût’un kavmini cezalandırmak üzere gönderildiklerini açıklamaları olayı; yine bu sûrelerde  ve A‘râf sûresinde Lût kavminin  acı âkıbeti anlatılmıştı (bk. A‘râf 7/80-84; Hûd 11/69-83; Hicr 15/51-77). Bu âyetlerde bazı detay farklarıyla aynı konuya yer verilmesi,  38-40.  âyetlerde Firavun ve adamlarının, 41-46. âyetlerde de başka bazı kavimlerin başına gelenlere kısa kısa değinilmesi, bir taraftan gösterilen açık kanıtlara rağmen taşkınlıklarını ve müslümanlara eziyetlerini  gittikçe arttıran müşrikler için bir uyarı, diğer taraftan da Resûl-i  Ekrem ve ona gönülden  bağlanan müminler için bir teselli anlamı taşımaktadır. Burada kıssanın misafir ağırlama bölümü, Allah Teâlâ’nın umulmadık bir anda ve biçimde, dilediği kullarını sıkıntıdan kurtarabileceğinin, bağnaz inkârcıları  da kötü âkıbete çarptırabileceğinin anlaşılmasına ışık tutmaktadır (Râzî, XXVIII, 210). Kur’an’ın bir kıssaya “Sana ulaştı mı?” şeklinde bir soruyla başlaması, o olayın önemine dikkat çektiğini ve Resûlullah’ın  onu ancak vahiy yoluyla bilebildiğini gösteren bir anlatım üslûbudur (Zemahşerî, IV, 28; İbn Âşûr, XXVI, 357). Misafirlerin  melek oluşu ve kelimenin  kök anlamları dikkate alınarak 24. âyette geçen mükremîn kelimesi  “değerli” diye çevrilmiştir. Bu kelimenin “ikram edilenler” anlamını esas alan müfessirler bununla, bizzat Hz. İbrâhim  ve eşinin misafirlere ikramda bulunup hizmet ettiklerine işaret edildiğini belirtirler (Taberî, XXVI, 207); fakat Allah Teâlâ katında ikrama mazhar oldukları için böyle nitelenmiş de olabilirler (İbn Atıyye, V, 177). 25. âyetin “(İçinden) ‘bunlar hiç de tanıdık kimseler değil’ demişti” diye tercüme edilen kısmı “(Onlara) ‘sizi tanımıyoruz, yabancısınız herhalde?’  demişti”  şeklinde  de anlaşılmıştır  (başka yorumlarla birlikte bk. Taberî, XXVI, 208; Zemahşerî, IV, 29-30). 26. âyette kullanılan  râğa fiili  daha çok, “sözünü bitirir  bitirmez, etrafındakilere belli etmeden bulunduğu yerden acele ayrılma”yı ifade eder (İbn Atıyye, V, 177). Olayın akışı dikkate alındığında Hz. İbrâhim farkına varılmayacak şekilde oradan ayrılması değil, gidiş sebebini belli etmeden yani onlara ikram hazırlığı gerekçesini açıklamadan müsaade almış olması muhtemeldir. Bu sebeple meâlde “belli etmeden ... gitti” denmiştir. Hûd sûresinin 69. âyetinde belirtildiği üzere, getirdiği buzağı kızartılmıştı. 27 ve 28. âyetlerde elçilerin yemeğe el sürmemeleri  sebebiyle Hz. İbrâhim’in endişelenmeye başladığı belirtilmektedir. Hûd sûresinin 70. âyetinde bu husus daha açık biçimde  ifade edilmiştir. Bu sebeple müfessirlerin bir kısmı, “Buyurmaz mısınız?” diye çevrilen cümleyi de onların yemediklerini  farketmesi üzerine söylediğini düşünmüşler ve “Niçin yemiyorsunuz ki?” şeklinde anlamışlardır. Kitâb-ı Mukaddes’te ise onların kendileri için hazırlanan yemeği yedikleri yazılıdır (bk. Tekvin, 18/8). Geleneğe göre misafirin kendisine ikram edilen yemeği yememesi hasmâne düşünceler taşıdığının işareti sayılıyordu. Bazı müfessirler Hz.İbrâhim’in endişesinin bu sebebe dayandığı kanaatindedir (İbn Atıyye, V, 178); İbn Abbas’tan gelen bir rivayete göre ise Hz. İbrâhim’in endişesi onların melek olduğunu sezmiş ve azap ile görevli olarak geldiklerini düşünmüş olmasından kaynaklanmıştı (Zemahşerî, IV, 30). 29. âyette Hz. İbrâhim’in eşinin  verilen haber (çocuk müjdesi) karşısındaki tepkisi tasvir edilirken kullanılan kelimelerle ilgili değişik açıklamalar yapılmıştır; bunlar, şaşkınlığını ifade eden bir ses çıkarması ve mahcubiyet içinde yahut hayretinden dolayı elleriyle yüzünü kapatmaya çalışması veya yüzüne vurması şeklinde özetlenebilir. Âyetin “heyecanla bağırarak” diye çevrilen kısmına, “Nazik bir edâ ile oraya geldi, yaklaştı” mânasını verenler de olmuştur (Zemahşerî, IV, 30; İbn Atıyye, V, 178; Şevkânî, V, 102). Lafzan “Yaşlı ve kısır bir kadın!” anlamına gelen hayret ifadesinin ögeleri iki türlü tamamlanarak açıklanmıştır: a) “Ben yaşlı ve kısır bir kadınım!”, b) “Yaşlı ve kısır bir kadın nasıl doğurabilir ki!” (İbn Atıyye, V, 178).  Bir kısım müfessirler bu âyetlerdeki anlatım tarzıyla, misafire hemen geliş sebebini sormayıp önce ikramda bulunma, ikram hazırlığını belli etmeden yapma, olabildiğince en iyi ikramda bulunma, nezaketle buyur etme gibi misafir ağırlama âdâbı ile ilgili bazı kurallara  işaret edildiği kanaatine ulaşmışlardır (Zemahşerî, IV, 30; Râzî, XXVIII, 213-214).  35-37. âyetler meleklerin  Hz. İbrâhim’le konuşmalarının devamı olmayıp burada olayla ilgili ek bir bilgi verilmektedir. 35. âyetin başında yer alan ve meâlde “derken” şeklinde karşılık verdiğimiz “fâ” harfi, meleklerin  Hz. İbrâhim’le  yapılan konuşmadan sonra burada belirtilen noktaya kadar geçen ve Hûd sûresinde anlatılan gelişmelere gönderme yapma anlamı içerir (İbn Âşûr, XXVII, 7)."
  },
  {
    "surahNo": 51,
    "ayahID": 36,
    "tefsirText": "Daha önce nâzil olan Hûd ve Hicr sûrelerinde, Hz. İbrâhim’e insan kılığında meleklerin  gelmesi, kendisi ve hanımı çok yaşlı oldukları halde, onlara bir oğul müjdelemeleri, ardından da Hz. Lût’un kavmini cezalandırmak üzere gönderildiklerini açıklamaları olayı; yine bu sûrelerde  ve A‘râf sûresinde Lût kavminin  acı âkıbeti anlatılmıştı (bk. A‘râf 7/80-84; Hûd 11/69-83; Hicr 15/51-77). Bu âyetlerde bazı detay farklarıyla aynı konuya yer verilmesi,  38-40.  âyetlerde Firavun ve adamlarının, 41-46. âyetlerde de başka bazı kavimlerin başına gelenlere kısa kısa değinilmesi, bir taraftan gösterilen açık kanıtlara rağmen taşkınlıklarını ve müslümanlara eziyetlerini  gittikçe arttıran müşrikler için bir uyarı, diğer taraftan da Resûl-i  Ekrem ve ona gönülden  bağlanan müminler için bir teselli anlamı taşımaktadır. Burada kıssanın misafir ağırlama bölümü, Allah Teâlâ’nın umulmadık bir anda ve biçimde, dilediği kullarını sıkıntıdan kurtarabileceğinin, bağnaz inkârcıları  da kötü âkıbete çarptırabileceğinin anlaşılmasına ışık tutmaktadır (Râzî, XXVIII, 210). Kur’an’ın bir kıssaya “Sana ulaştı mı?” şeklinde bir soruyla başlaması, o olayın önemine dikkat çektiğini ve Resûlullah’ın  onu ancak vahiy yoluyla bilebildiğini gösteren bir anlatım üslûbudur (Zemahşerî, IV, 28; İbn Âşûr, XXVI, 357). Misafirlerin  melek oluşu ve kelimenin  kök anlamları dikkate alınarak 24. âyette geçen mükremîn kelimesi  “değerli” diye çevrilmiştir. Bu kelimenin “ikram edilenler” anlamını esas alan müfessirler bununla, bizzat Hz. İbrâhim  ve eşinin misafirlere ikramda bulunup hizmet ettiklerine işaret edildiğini belirtirler (Taberî, XXVI, 207); fakat Allah Teâlâ katında ikrama mazhar oldukları için böyle nitelenmiş de olabilirler (İbn Atıyye, V, 177). 25. âyetin “(İçinden) ‘bunlar hiç de tanıdık kimseler değil’ demişti” diye tercüme edilen kısmı “(Onlara) ‘sizi tanımıyoruz, yabancısınız herhalde?’  demişti”  şeklinde  de anlaşılmıştır  (başka yorumlarla birlikte bk. Taberî, XXVI, 208; Zemahşerî, IV, 29-30). 26. âyette kullanılan  râğa fiili  daha çok, “sözünü bitirir  bitirmez, etrafındakilere belli etmeden bulunduğu yerden acele ayrılma”yı ifade eder (İbn Atıyye, V, 177). Olayın akışı dikkate alındığında Hz. İbrâhim farkına varılmayacak şekilde oradan ayrılması değil, gidiş sebebini belli etmeden yani onlara ikram hazırlığı gerekçesini açıklamadan müsaade almış olması muhtemeldir. Bu sebeple meâlde “belli etmeden ... gitti” denmiştir. Hûd sûresinin 69. âyetinde belirtildiği üzere, getirdiği buzağı kızartılmıştı. 27 ve 28. âyetlerde elçilerin yemeğe el sürmemeleri  sebebiyle Hz. İbrâhim’in endişelenmeye başladığı belirtilmektedir. Hûd sûresinin 70. âyetinde bu husus daha açık biçimde  ifade edilmiştir. Bu sebeple müfessirlerin bir kısmı, “Buyurmaz mısınız?” diye çevrilen cümleyi de onların yemediklerini  farketmesi üzerine söylediğini düşünmüşler ve “Niçin yemiyorsunuz ki?” şeklinde anlamışlardır. Kitâb-ı Mukaddes’te ise onların kendileri için hazırlanan yemeği yedikleri yazılıdır (bk. Tekvin, 18/8). Geleneğe göre misafirin kendisine ikram edilen yemeği yememesi hasmâne düşünceler taşıdığının işareti sayılıyordu. Bazı müfessirler Hz.İbrâhim’in endişesinin bu sebebe dayandığı kanaatindedir (İbn Atıyye, V, 178); İbn Abbas’tan gelen bir rivayete göre ise Hz. İbrâhim’in endişesi onların melek olduğunu sezmiş ve azap ile görevli olarak geldiklerini düşünmüş olmasından kaynaklanmıştı (Zemahşerî, IV, 30). 29. âyette Hz. İbrâhim’in eşinin  verilen haber (çocuk müjdesi) karşısındaki tepkisi tasvir edilirken kullanılan kelimelerle ilgili değişik açıklamalar yapılmıştır; bunlar, şaşkınlığını ifade eden bir ses çıkarması ve mahcubiyet içinde yahut hayretinden dolayı elleriyle yüzünü kapatmaya çalışması veya yüzüne vurması şeklinde özetlenebilir. Âyetin “heyecanla bağırarak” diye çevrilen kısmına, “Nazik bir edâ ile oraya geldi, yaklaştı” mânasını verenler de olmuştur (Zemahşerî, IV, 30; İbn Atıyye, V, 178; Şevkânî, V, 102). Lafzan “Yaşlı ve kısır bir kadın!” anlamına gelen hayret ifadesinin ögeleri iki türlü tamamlanarak açıklanmıştır: a) “Ben yaşlı ve kısır bir kadınım!”, b) “Yaşlı ve kısır bir kadın nasıl doğurabilir ki!” (İbn Atıyye, V, 178).  Bir kısım müfessirler bu âyetlerdeki anlatım tarzıyla, misafire hemen geliş sebebini sormayıp önce ikramda bulunma, ikram hazırlığını belli etmeden yapma, olabildiğince en iyi ikramda bulunma, nezaketle buyur etme gibi misafir ağırlama âdâbı ile ilgili bazı kurallara  işaret edildiği kanaatine ulaşmışlardır (Zemahşerî, IV, 30; Râzî, XXVIII, 213-214).  35-37. âyetler meleklerin  Hz. İbrâhim’le konuşmalarının devamı olmayıp burada olayla ilgili ek bir bilgi verilmektedir. 35. âyetin başında yer alan ve meâlde “derken” şeklinde karşılık verdiğimiz “fâ” harfi, meleklerin  Hz. İbrâhim’le  yapılan konuşmadan sonra burada belirtilen noktaya kadar geçen ve Hûd sûresinde anlatılan gelişmelere gönderme yapma anlamı içerir (İbn Âşûr, XXVII, 7)."
  },
  {
    "surahNo": 51,
    "ayahID": 37,
    "tefsirText": "Daha önce nâzil olan Hûd ve Hicr sûrelerinde, Hz. İbrâhim’e insan kılığında meleklerin  gelmesi, kendisi ve hanımı çok yaşlı oldukları halde, onlara bir oğul müjdelemeleri, ardından da Hz. Lût’un kavmini cezalandırmak üzere gönderildiklerini açıklamaları olayı; yine bu sûrelerde  ve A‘râf sûresinde Lût kavminin  acı âkıbeti anlatılmıştı (bk. A‘râf 7/80-84; Hûd 11/69-83; Hicr 15/51-77). Bu âyetlerde bazı detay farklarıyla aynı konuya yer verilmesi,  38-40.  âyetlerde Firavun ve adamlarının, 41-46. âyetlerde de başka bazı kavimlerin başına gelenlere kısa kısa değinilmesi, bir taraftan gösterilen açık kanıtlara rağmen taşkınlıklarını ve müslümanlara eziyetlerini  gittikçe arttıran müşrikler için bir uyarı, diğer taraftan da Resûl-i  Ekrem ve ona gönülden  bağlanan müminler için bir teselli anlamı taşımaktadır. Burada kıssanın misafir ağırlama bölümü, Allah Teâlâ’nın umulmadık bir anda ve biçimde, dilediği kullarını sıkıntıdan kurtarabileceğinin, bağnaz inkârcıları  da kötü âkıbete çarptırabileceğinin anlaşılmasına ışık tutmaktadır (Râzî, XXVIII, 210). Kur’an’ın bir kıssaya “Sana ulaştı mı?” şeklinde bir soruyla başlaması, o olayın önemine dikkat çektiğini ve Resûlullah’ın  onu ancak vahiy yoluyla bilebildiğini gösteren bir anlatım üslûbudur (Zemahşerî, IV, 28; İbn Âşûr, XXVI, 357). Misafirlerin  melek oluşu ve kelimenin  kök anlamları dikkate alınarak 24. âyette geçen mükremîn kelimesi  “değerli” diye çevrilmiştir. Bu kelimenin “ikram edilenler” anlamını esas alan müfessirler bununla, bizzat Hz. İbrâhim  ve eşinin misafirlere ikramda bulunup hizmet ettiklerine işaret edildiğini belirtirler (Taberî, XXVI, 207); fakat Allah Teâlâ katında ikrama mazhar oldukları için böyle nitelenmiş de olabilirler (İbn Atıyye, V, 177). 25. âyetin “(İçinden) ‘bunlar hiç de tanıdık kimseler değil’ demişti” diye tercüme edilen kısmı “(Onlara) ‘sizi tanımıyoruz, yabancısınız herhalde?’  demişti”  şeklinde  de anlaşılmıştır  (başka yorumlarla birlikte bk. Taberî, XXVI, 208; Zemahşerî, IV, 29-30). 26. âyette kullanılan  râğa fiili  daha çok, “sözünü bitirir  bitirmez, etrafındakilere belli etmeden bulunduğu yerden acele ayrılma”yı ifade eder (İbn Atıyye, V, 177). Olayın akışı dikkate alındığında Hz. İbrâhim farkına varılmayacak şekilde oradan ayrılması değil, gidiş sebebini belli etmeden yani onlara ikram hazırlığı gerekçesini açıklamadan müsaade almış olması muhtemeldir. Bu sebeple meâlde “belli etmeden ... gitti” denmiştir. Hûd sûresinin 69. âyetinde belirtildiği üzere, getirdiği buzağı kızartılmıştı. 27 ve 28. âyetlerde elçilerin yemeğe el sürmemeleri  sebebiyle Hz. İbrâhim’in endişelenmeye başladığı belirtilmektedir. Hûd sûresinin 70. âyetinde bu husus daha açık biçimde  ifade edilmiştir. Bu sebeple müfessirlerin bir kısmı, “Buyurmaz mısınız?” diye çevrilen cümleyi de onların yemediklerini  farketmesi üzerine söylediğini düşünmüşler ve “Niçin yemiyorsunuz ki?” şeklinde anlamışlardır. Kitâb-ı Mukaddes’te ise onların kendileri için hazırlanan yemeği yedikleri yazılıdır (bk. Tekvin, 18/8). Geleneğe göre misafirin kendisine ikram edilen yemeği yememesi hasmâne düşünceler taşıdığının işareti sayılıyordu. Bazı müfessirler Hz.İbrâhim’in endişesinin bu sebebe dayandığı kanaatindedir (İbn Atıyye, V, 178); İbn Abbas’tan gelen bir rivayete göre ise Hz. İbrâhim’in endişesi onların melek olduğunu sezmiş ve azap ile görevli olarak geldiklerini düşünmüş olmasından kaynaklanmıştı (Zemahşerî, IV, 30). 29. âyette Hz. İbrâhim’in eşinin  verilen haber (çocuk müjdesi) karşısındaki tepkisi tasvir edilirken kullanılan kelimelerle ilgili değişik açıklamalar yapılmıştır; bunlar, şaşkınlığını ifade eden bir ses çıkarması ve mahcubiyet içinde yahut hayretinden dolayı elleriyle yüzünü kapatmaya çalışması veya yüzüne vurması şeklinde özetlenebilir. Âyetin “heyecanla bağırarak” diye çevrilen kısmına, “Nazik bir edâ ile oraya geldi, yaklaştı” mânasını verenler de olmuştur (Zemahşerî, IV, 30; İbn Atıyye, V, 178; Şevkânî, V, 102). Lafzan “Yaşlı ve kısır bir kadın!” anlamına gelen hayret ifadesinin ögeleri iki türlü tamamlanarak açıklanmıştır: a) “Ben yaşlı ve kısır bir kadınım!”, b) “Yaşlı ve kısır bir kadın nasıl doğurabilir ki!” (İbn Atıyye, V, 178).  Bir kısım müfessirler bu âyetlerdeki anlatım tarzıyla, misafire hemen geliş sebebini sormayıp önce ikramda bulunma, ikram hazırlığını belli etmeden yapma, olabildiğince en iyi ikramda bulunma, nezaketle buyur etme gibi misafir ağırlama âdâbı ile ilgili bazı kurallara  işaret edildiği kanaatine ulaşmışlardır (Zemahşerî, IV, 30; Râzî, XXVIII, 213-214).  35-37. âyetler meleklerin  Hz. İbrâhim’le konuşmalarının devamı olmayıp burada olayla ilgili ek bir bilgi verilmektedir. 35. âyetin başında yer alan ve meâlde “derken” şeklinde karşılık verdiğimiz “fâ” harfi, meleklerin  Hz. İbrâhim’le  yapılan konuşmadan sonra burada belirtilen noktaya kadar geçen ve Hûd sûresinde anlatılan gelişmelere gönderme yapma anlamı içerir (İbn Âşûr, XXVII, 7)."
  },
  {
    "surahNo": 51,
    "ayahID": 38,
    "tefsirText": "İlk âyetteki sultân kelimesi bu bağlamda “ açık kanıt”  anlamına gelmektedir (İbn Atıyye, V, 179) ve bununla Hz. Mûsâ’nın Firavun’un önünde sergilediği mûcizeler kastedilmektedir (İbn Âşûr, XXVII, 10). 39. âyetin  “saltanatı sebebiyle”  diye çevrilen kısmı, daha çok “ sahip olduğu bütün güçleri, askerlerini, iktidarı elinde bulunduruyor olmayı kullanarak”  veya  “var gücüyle”  mânalarıyla açıklanmıştır (Zemahşerî, IV, 31; İbn Atıyye, V, 179-180). 40. âyetin son cümlesi –meâlde tercih edilen mânaya göre– Firavun’un  can verirken  duyduğu pişmanlığa işaret etmektedir (krş. Yûnus 10/90-92). Müfessirlerin bir kısmı bu cümleyi,  “O, kınanacak işler yapmaktaydı”  şeklinde anlamışlardır ki, bu takdirde Firavun’un  daha önce yaptığı kötülüklere işaret edilmiş olur (Taberî, XXVII, 3-4; Firavun ve Hz. Mûsâ’nın ona karşı mücadelesi hakkında bk. A‘râf 7/103 vd.; Yûnus 10/75-93;  Kasas 28/31-32).   "
  },
  {
    "surahNo": 51,
    "ayahID": 39,
    "tefsirText": "İlk âyetteki sultân kelimesi bu bağlamda “açık kanıt” anlamına gelmektedir (İbn Atıyye, V, 179) ve bununla Hz. Mûsâ’nın Firavun’un önünde sergilediği mûcizeler kastedilmektedir (İbn Âşûr, XXVII, 10). 39. âyetin “saltanatı sebebiyle” diye çevrilen kısmı, daha çok “sahip olduğu bütün güçleri, askerlerini, iktidarı elinde bulunduruyor olmayı kullanarak” veya “var gücüyle” mânalarıyla açıklanmıştır (Zemahşerî, IV, 31; İbn Atıyye, V, 179-180). 40. âyetin son cümlesi –meâlde tercih edilen mânaya göre– Firavun’un  can verirken  duyduğu pişmanlığa işaret etmektedir (krş. Yûnus 10/90-92). Müfessirlerin bir kısmı bu cümleyi, “O, kınanacak işler yapmaktaydı” şeklinde anlamışlardır ki, bu takdirde Firavun’un  daha önce yaptığı kötülüklere işaret edilmiş olur (Taberî, XXVII, 3-4; Firavun ve Hz. Mûsâ’nın ona karşı mücadelesi hakkında bk. A‘râf 7/103 vd.; Yûnus 10/75-93;  Kasas 28/31-32)."
  },
  {
    "surahNo": 51,
    "ayahID": 40,
    "tefsirText": "İlk âyetteki sultân kelimesi bu bağlamda “açık kanıt” anlamına gelmektedir (İbn Atıyye, V, 179) ve bununla Hz. Mûsâ’nın Firavun’un önünde sergilediği mûcizeler kastedilmektedir (İbn Âşûr, XXVII, 10). 39. âyetin “saltanatı sebebiyle” diye çevrilen kısmı, daha çok “sahip olduğu bütün güçleri, askerlerini, iktidarı elinde bulunduruyor olmayı kullanarak” veya “var gücüyle” mânalarıyla açıklanmıştır (Zemahşerî, IV, 31; İbn Atıyye, V, 179-180). 40. âyetin son cümlesi –meâlde tercih edilen mânaya göre– Firavun’un  can verirken  duyduğu pişmanlığa işaret etmektedir (krş. Yûnus 10/90-92). Müfessirlerin bir kısmı bu cümleyi, “O, kınanacak işler yapmaktaydı” şeklinde anlamışlardır ki, bu takdirde Firavun’un  daha önce yaptığı kötülüklere işaret edilmiş olur (Taberî, XXVII, 3-4; Firavun ve Hz. Mûsâ’nın ona karşı mücadelesi hakkında bk. A‘râf 7/103 vd.; Yûnus 10/75-93;  Kasas 28/31-32)."
  },
  {
    "surahNo": 51,
    "ayahID": 41,
    "tefsirText": "Âd Hûd peygamberin,  Semûd da Sâlih peygamberin  kavminin adı olup Kur’ân-ı  Kerîm’de bu toplumların  ve Nûh kavminin  yapılan bütün ilâhî uyarıları  hafife  almaları ve inkârcılıkta direnmeleri sebebiyle helâk edilmelerine değişik vesilelerle dikkat çekilmiştir (Âd hakkında bk. A‘râf 7/65-72; Hûd 11/50-60; Semûd hakkında bk. A‘râf 7/73-79; Hûd 11/61-68; Nûh kavmi hakkında bk. A‘râf 7/59-64;  Yûnus 10/71-74; Hûd 11/25-49).   "
  },
  {
    "surahNo": 51,
    "ayahID": 42,
    "tefsirText": "Âd Hûd peygamberin,  Semûd da Sâlih peygamberin  kavminin adı olup Kur’ân-ı  Kerîm’de bu toplumların  ve Nûh kavminin  yapılan bütün ilâhî uyarıları  hafife  almaları ve inkârcılıkta direnmeleri sebebiyle helâk edilmelerine değişik vesilelerle dikkat çekilmiştir (Âd hakkında bk. A‘râf 7/65-72; Hûd 11/50-60; Semûd hakkında bk. A‘râf 7/73-79; Hûd 11/61-68; Nûh kavmi hakkında bk. A‘râf 7/59-64;  Yûnus 10/71-74; Hûd 11/25-49)."
  },
  {
    "surahNo": 51,
    "ayahID": 43,
    "tefsirText": "Âd Hûd peygamberin,  Semûd da Sâlih peygamberin  kavminin adı olup Kur’ân-ı  Kerîm’de bu toplumların  ve Nûh kavminin  yapılan bütün ilâhî uyarıları  hafife  almaları ve inkârcılıkta direnmeleri sebebiyle helâk edilmelerine değişik vesilelerle dikkat çekilmiştir (Âd hakkında bk. A‘râf 7/65-72; Hûd 11/50-60; Semûd hakkında bk. A‘râf 7/73-79; Hûd 11/61-68; Nûh kavmi hakkında bk. A‘râf 7/59-64;  Yûnus 10/71-74; Hûd 11/25-49)."
  },
  {
    "surahNo": 51,
    "ayahID": 44,
    "tefsirText": "Âd Hûd peygamberin,  Semûd da Sâlih peygamberin  kavminin adı olup Kur’ân-ı  Kerîm’de bu toplumların  ve Nûh kavminin  yapılan bütün ilâhî uyarıları  hafife  almaları ve inkârcılıkta direnmeleri sebebiyle helâk edilmelerine değişik vesilelerle dikkat çekilmiştir (Âd hakkında bk. A‘râf 7/65-72; Hûd 11/50-60; Semûd hakkında bk. A‘râf 7/73-79; Hûd 11/61-68; Nûh kavmi hakkında bk. A‘râf 7/59-64;  Yûnus 10/71-74; Hûd 11/25-49)."
  },
  {
    "surahNo": 51,
    "ayahID": 45,
    "tefsirText": "Âd Hûd peygamberin,  Semûd da Sâlih peygamberin  kavminin adı olup Kur’ân-ı  Kerîm’de bu toplumların  ve Nûh kavminin  yapılan bütün ilâhî uyarıları  hafife  almaları ve inkârcılıkta direnmeleri sebebiyle helâk edilmelerine değişik vesilelerle dikkat çekilmiştir (Âd hakkında bk. A‘râf 7/65-72; Hûd 11/50-60; Semûd hakkında bk. A‘râf 7/73-79; Hûd 11/61-68; Nûh kavmi hakkında bk. A‘râf 7/59-64;  Yûnus 10/71-74; Hûd 11/25-49)."
  },
  {
    "surahNo": 51,
    "ayahID": 46,
    "tefsirText": "Âd Hûd peygamberin,  Semûd da Sâlih peygamberin  kavminin adı olup Kur’ân-ı  Kerîm’de bu toplumların  ve Nûh kavminin  yapılan bütün ilâhî uyarıları  hafife  almaları ve inkârcılıkta direnmeleri sebebiyle helâk edilmelerine değişik vesilelerle dikkat çekilmiştir (Âd hakkında bk. A‘râf 7/65-72; Hûd 11/50-60; Semûd hakkında bk. A‘râf 7/73-79; Hûd 11/61-68; Nûh kavmi hakkında bk. A‘râf 7/59-64;  Yûnus 10/71-74; Hûd 11/25-49)."
  },
  {
    "surahNo": 51,
    "ayahID": 47,
    "tefsirText": "İlk üç âyette Cenâb-ı Allah’ın  sonsuz kudretini gösteren ve her an yakın çevremizde gözlemleyebildiğimiz üç çeşit kanıta değinilmekte, 50-51. âyetlerde de bunlardan  çıkarılması gereken sonuç peygamberinin dilinden bir uyarı tarzında ifade edilmektedir: Başka kaçacak, sığınılacak yer yoktur, yalnız Allah’a sığınmak, O’nun gösterdiği yolda yürümek gerekir; O’nun yanında başka tanrılar uydurmak akıl ve iz‘an sahibi varlıklara yaraşmaz.     47. âyette geçen eyd kelimesinin  “kuvvet, kudret”  veya “eller” mânalarına göre değişik yorumlar yapılmıştır; bu yorumlar, göğün muhteşem yapısı ve düzeninin  yüce Allah’ın kudretine  bağlı olduğunu ifade etme noktasında birleşir (Râzî, XXVIII,  226).  “Şüphesiz biz genişletmekteyiz”  diye çevrilen cümle için yapılan başlıca yorumlar şunlardır: a) Biz vüs’at yani genişlik ve kudret sahibiyiz; semadaki bu ihtişamı sağlamakla kudretimizden bir şey eksildiği sanılmamalıdır, dilesek daha da genişletiriz. Bakara sûresinin  255 ve Kaf sûresinin 38. âyetlerindeki içerik ve üslûp bu mânayı çağrıştırmaktadır. b) Hiçbir şeye muhtaç olmadığımız gibi nimetleri bol bol ihsan eden de biziz; sıkıntıları giderir, darda kalanlara genişlik veririz (Şevkânî, V, 105; Elmalılı, VI, 4542-4543). c) Evreni genişletmekteyiz. Bu yorum  daha çok, uzay cisimlerinin birbirinden uzaklaştığı ve aralarındaki mesafenin gitgide arttığı yönündeki bilimsel tesbitten hareketle ortaya konan  “genişleme teorisi”  ışığında yapılmıştır (bk. Celal Kırca, s. 62-63; eski dönemlerin âlimlerinden  bu yorumu destekleyen bazı açıklamalar için bk. Celâl Yeniçeri, s. 110-115). Gök kelimesinin Kur’an’daki kullanımları dikkate alınarak genişletilen şey, bu ve benzeri bağlamlarda “evren” (Esed, III, 1070-1071), “ dünyanın dışındaki bütün kâinat”  (Celal Kırca, s. 62) anlamlarında yorumlanabilmektedir. Râzî göğün binaya ve yerin döşeğe benzetilmesini, göğün ana yapısında değişme olmamasına, yerin ise genişleme-daralma, denizlerinin  karaya dönüşmesi gibi değişkenliklere açık olmasına bağlar (XXVIII, 225-226; göklerin ve yerin  yaratılması hakkında  bk. Bakara 2/22, 29).      Müfessirler  “her şeyden çift çift yaratma ”nın anlamını açıklarken daha çok  “gece-gündüz, erkek-dişi, yer-gök, insan-cin, iman-küfür, ay-güneş”  gibi karşıtlık örnekleri üzerinde durmuşlardır. Taberî bunu  “Cenâb-ı Allah’ın her yarattığının yanı sıra amaç ve işlevi itibariyle ondan farklı bir ikincisini yaratması”  şeklinde anlamanın uygun olacağı kanaatindedir. Yine Taberî’nin izahına göre burada esas amaç Allah’ın yaratma sıfatına dikkat çekmektir.  O’nun yaratmasını –meselâ ateşin yakma özelliği gibi– tek sonuçlu olarak algılamamak gerekir, O dilediği her şeyi dilediği biçimde yaratma gücüne sahiptir  (XXVII, 8-9). Elmalılı, bu konudaki görüşleri özetledikten sonra, Beyzâvî’nin “her cinsten iki nevi bulunduğu” tarzındaki yorumunu öncekileri  de içine alması itibariyle daha kapsamlı bulur. Bununla birlikte o, âyetteki  “her şey ” ifadesinin sadece cinsleri değil fertleri de kapsadığını dikkate alarak, burada dış âlemdekiler ile onların zihindeki formlarının uyumlu eşleşmesiyle tecelli eden idrak olayına da işaret bulunduğu yorumunu yapar; herhangi bir şey hakkında meydana gelen şuur hâdisesinde bu ikiliğin kaçınılmaz olduğunu, bu ikilik içinde birleştirilmeden hiçbir şeyin tasdik edilemeyeceğini, tefekkür ve tezekkürde bulunulamayacağını, âyetin sonunda yer alan  “ki inceden inceye düşünesiniz”  ifadesinin de bunu desteklediğini belirtir (bk. VI, 4543-4544; ayrıca bk. Yâsîn 36/36)      49. âyetin son cümlesi hem bu âyette hem de önceki iki âyette belirtilenler üzerinde düşünülmesini kapsadığından (Zemahşerî, IV, 31), sırf bulunduğu âyete bağlı düşünülmemesi için meâlinde bu cümleyi “İnceden inceye düşünesiniz diye!” şeklinde sona aldık.    "
  },
  {
    "surahNo": 51,
    "ayahID": 48,
    "tefsirText": "İlk üç âyette Cenâb-ı Allah’ın  sonsuz kudretini gösteren ve her an yakın çevremizde gözlemleyebildiğimiz üç çeşit kanıta değinilmekte, 50-51. âyetlerde de bunlardan  çıkarılması gereken sonuç peygamberinin dilinden bir uyarı tarzında ifade edilmektedir: Başka kaçacak, sığınılacak yer yoktur, yalnız Allah’a sığınmak, O’nun gösterdiği yolda yürümek gerekir; O’nun yanında başka tanrılar uydurmak akıl ve iz‘an sahibi varlıklara yaraşmaz.  47. âyette geçen eyd kelimesinin “kuvvet, kudret” veya “eller” mânalarına göre değişik yorumlar yapılmıştır; bu yorumlar, göğün muhteşem yapısı ve düzeninin  yüce Allah’ın kudretine  bağlı olduğunu ifade etme noktasında birleşir (Râzî, XXVIII,  226). “Şüphesiz biz genişletmekteyiz” diye çevrilen cümle için yapılan başlıca yorumlar şunlardır: a) Biz vüs’at yani genişlik ve kudret sahibiyiz; semadaki bu ihtişamı sağlamakla kudretimizden bir şey eksildiği sanılmamalıdır, dilesek daha da genişletiriz. Bakara sûresinin  255 ve Kaf sûresinin 38. âyetlerindeki içerik ve üslûp bu mânayı çağrıştırmaktadır. b) Hiçbir şeye muhtaç olmadığımız gibi nimetleri bol bol ihsan eden de biziz; sıkıntıları giderir, darda kalanlara genişlik veririz (Şevkânî, V, 105; Elmalılı, VI, 4542-4543). c) Evreni genişletmekteyiz. Bu yorum  daha çok, uzay cisimlerinin birbirinden uzaklaştığı ve aralarındaki mesafenin gitgide arttığı yönündeki bilimsel tesbitten hareketle ortaya konan “genişleme teorisi” ışığında yapılmıştır (bk. Celal Kırca, s. 62-63; eski dönemlerin âlimlerinden  bu yorumu destekleyen bazı açıklamalar için bk. Celâl Yeniçeri, s. 110-115). Gök kelimesinin Kur’an’daki kullanımları dikkate alınarak genişletilen şey, bu ve benzeri bağlamlarda “evren” (Esed, III, 1070-1071), “dünyanın dışındaki bütün kâinat” (Celal Kırca, s. 62) anlamlarında yorumlanabilmektedir. Râzî göğün binaya ve yerin döşeğe benzetilmesini, göğün ana yapısında değişme olmamasına, yerin ise genişleme-daralma, denizlerinin  karaya dönüşmesi gibi değişkenliklere açık olmasına bağlar (XXVIII, 225-226; göklerin ve yerin  yaratılması hakkında  bk. Bakara 2/22, 29).  Müfessirler “her şeyden çift çift yaratma”nın anlamını açıklarken daha çok “gece-gündüz, erkek-dişi, yer-gök, insan-cin, iman-küfür, ay-güneş” gibi karşıtlık örnekleri üzerinde durmuşlardır. Taberî bunu “Cenâb-ı Allah’ın her yarattığının yanı sıra amaç ve işlevi itibariyle ondan farklı bir ikincisini yaratması” şeklinde anlamanın uygun olacağı kanaatindedir. Yine Taberî’nin izahına göre burada esas amaç Allah’ın yaratma sıfatına dikkat çekmektir.  O’nun yaratmasını –meselâ ateşin yakma özelliği gibi– tek sonuçlu olarak algılamamak gerekir, O dilediği her şeyi dilediği biçimde yaratma gücüne sahiptir  (XXVII, 8-9). Elmalılı, bu konudaki görüşleri özetledikten sonra, Beyzâvî’nin “her cinsten iki nevi bulunduğu” tarzındaki yorumunu öncekileri  de içine alması itibariyle daha kapsamlı bulur. Bununla birlikte o, âyetteki “her şey” ifadesinin sadece cinsleri değil fertleri de kapsadığını dikkate alarak, burada dış âlemdekiler ile onların zihindeki formlarının uyumlu eşleşmesiyle tecelli eden idrak olayına da işaret bulunduğu yorumunu yapar; herhangi bir şey hakkında meydana gelen şuur hâdisesinde bu ikiliğin kaçınılmaz olduğunu, bu ikilik içinde birleştirilmeden hiçbir şeyin tasdik edilemeyeceğini, tefekkür ve tezekkürde bulunulamayacağını, âyetin sonunda yer alan “ki inceden inceye düşünesiniz” ifadesinin de bunu desteklediğini belirtir (bk. VI, 4543-4544; ayrıca bk. Yâsîn 36/36). 49. âyetin son cümlesi hem bu âyette hem de önceki iki âyette belirtilenler üzerinde düşünülmesini kapsadığından (Zemahşerî, IV, 31), sırf bulunduğu âyete bağlı düşünülmemesi için meâlinde bu cümleyi “İnceden inceye düşünesiniz diye!” şeklinde sona aldık."
  },
  {
    "surahNo": 51,
    "ayahID": 49,
    "tefsirText": "İlk üç âyette Cenâb-ı Allah’ın  sonsuz kudretini gösteren ve her an yakın çevremizde gözlemleyebildiğimiz üç çeşit kanıta değinilmekte, 50-51. âyetlerde de bunlardan  çıkarılması gereken sonuç peygamberinin dilinden bir uyarı tarzında ifade edilmektedir: Başka kaçacak, sığınılacak yer yoktur, yalnız Allah’a sığınmak, O’nun gösterdiği yolda yürümek gerekir; O’nun yanında başka tanrılar uydurmak akıl ve iz‘an sahibi varlıklara yaraşmaz.  47. âyette geçen eyd kelimesinin “kuvvet, kudret” veya “eller” mânalarına göre değişik yorumlar yapılmıştır; bu yorumlar, göğün muhteşem yapısı ve düzeninin  yüce Allah’ın kudretine  bağlı olduğunu ifade etme noktasında birleşir (Râzî, XXVIII,  226). “Şüphesiz biz genişletmekteyiz” diye çevrilen cümle için yapılan başlıca yorumlar şunlardır: a) Biz vüs’at yani genişlik ve kudret sahibiyiz; semadaki bu ihtişamı sağlamakla kudretimizden bir şey eksildiği sanılmamalıdır, dilesek daha da genişletiriz. Bakara sûresinin  255 ve Kaf sûresinin 38. âyetlerindeki içerik ve üslûp bu mânayı çağrıştırmaktadır. b) Hiçbir şeye muhtaç olmadığımız gibi nimetleri bol bol ihsan eden de biziz; sıkıntıları giderir, darda kalanlara genişlik veririz (Şevkânî, V, 105; Elmalılı, VI, 4542-4543). c) Evreni genişletmekteyiz. Bu yorum  daha çok, uzay cisimlerinin birbirinden uzaklaştığı ve aralarındaki mesafenin gitgide arttığı yönündeki bilimsel tesbitten hareketle ortaya konan “genişleme teorisi” ışığında yapılmıştır (bk. Celal Kırca, s. 62-63; eski dönemlerin âlimlerinden  bu yorumu destekleyen bazı açıklamalar için bk. Celâl Yeniçeri, s. 110-115). Gök kelimesinin Kur’an’daki kullanımları dikkate alınarak genişletilen şey, bu ve benzeri bağlamlarda “evren” (Esed, III, 1070-1071), “dünyanın dışındaki bütün kâinat” (Celal Kırca, s. 62) anlamlarında yorumlanabilmektedir. Râzî göğün binaya ve yerin döşeğe benzetilmesini, göğün ana yapısında değişme olmamasına, yerin ise genişleme-daralma, denizlerinin  karaya dönüşmesi gibi değişkenliklere açık olmasına bağlar (XXVIII, 225-226; göklerin ve yerin  yaratılması hakkında  bk. Bakara 2/22, 29).  Müfessirler “her şeyden çift çift yaratma”nın anlamını açıklarken daha çok “gece-gündüz, erkek-dişi, yer-gök, insan-cin, iman-küfür, ay-güneş” gibi karşıtlık örnekleri üzerinde durmuşlardır. Taberî bunu “Cenâb-ı Allah’ın her yarattığının yanı sıra amaç ve işlevi itibariyle ondan farklı bir ikincisini yaratması” şeklinde anlamanın uygun olacağı kanaatindedir. Yine Taberî’nin izahına göre burada esas amaç Allah’ın yaratma sıfatına dikkat çekmektir.  O’nun yaratmasını –meselâ ateşin yakma özelliği gibi– tek sonuçlu olarak algılamamak gerekir, O dilediği her şeyi dilediği biçimde yaratma gücüne sahiptir  (XXVII, 8-9). Elmalılı, bu konudaki görüşleri özetledikten sonra, Beyzâvî’nin “her cinsten iki nevi bulunduğu” tarzındaki yorumunu öncekileri  de içine alması itibariyle daha kapsamlı bulur. Bununla birlikte o, âyetteki “her şey” ifadesinin sadece cinsleri değil fertleri de kapsadığını dikkate alarak, burada dış âlemdekiler ile onların zihindeki formlarının uyumlu eşleşmesiyle tecelli eden idrak olayına da işaret bulunduğu yorumunu yapar; herhangi bir şey hakkında meydana gelen şuur hâdisesinde bu ikiliğin kaçınılmaz olduğunu, bu ikilik içinde birleştirilmeden hiçbir şeyin tasdik edilemeyeceğini, tefekkür ve tezekkürde bulunulamayacağını, âyetin sonunda yer alan “ki inceden inceye düşünesiniz” ifadesinin de bunu desteklediğini belirtir (bk. VI, 4543-4544; ayrıca bk. Yâsîn 36/36). 49. âyetin son cümlesi hem bu âyette hem de önceki iki âyette belirtilenler üzerinde düşünülmesini kapsadığından (Zemahşerî, IV, 31), sırf bulunduğu âyete bağlı düşünülmemesi için meâlinde bu cümleyi “İnceden inceye düşünesiniz diye!” şeklinde sona aldık."
  },
  {
    "surahNo": 51,
    "ayahID": 50,
    "tefsirText": "İlk üç âyette Cenâb-ı Allah’ın  sonsuz kudretini gösteren ve her an yakın çevremizde gözlemleyebildiğimiz üç çeşit kanıta değinilmekte, 50-51. âyetlerde de bunlardan  çıkarılması gereken sonuç peygamberinin dilinden bir uyarı tarzında ifade edilmektedir: Başka kaçacak, sığınılacak yer yoktur, yalnız Allah’a sığınmak, O’nun gösterdiği yolda yürümek gerekir; O’nun yanında başka tanrılar uydurmak akıl ve iz‘an sahibi varlıklara yaraşmaz.  47. âyette geçen eyd kelimesinin “kuvvet, kudret” veya “eller” mânalarına göre değişik yorumlar yapılmıştır; bu yorumlar, göğün muhteşem yapısı ve düzeninin  yüce Allah’ın kudretine  bağlı olduğunu ifade etme noktasında birleşir (Râzî, XXVIII,  226). “Şüphesiz biz genişletmekteyiz” diye çevrilen cümle için yapılan başlıca yorumlar şunlardır: a) Biz vüs’at yani genişlik ve kudret sahibiyiz; semadaki bu ihtişamı sağlamakla kudretimizden bir şey eksildiği sanılmamalıdır, dilesek daha da genişletiriz. Bakara sûresinin  255 ve Kaf sûresinin 38. âyetlerindeki içerik ve üslûp bu mânayı çağrıştırmaktadır. b) Hiçbir şeye muhtaç olmadığımız gibi nimetleri bol bol ihsan eden de biziz; sıkıntıları giderir, darda kalanlara genişlik veririz (Şevkânî, V, 105; Elmalılı, VI, 4542-4543). c) Evreni genişletmekteyiz. Bu yorum  daha çok, uzay cisimlerinin birbirinden uzaklaştığı ve aralarındaki mesafenin gitgide arttığı yönündeki bilimsel tesbitten hareketle ortaya konan “genişleme teorisi” ışığında yapılmıştır (bk. Celal Kırca, s. 62-63; eski dönemlerin âlimlerinden  bu yorumu destekleyen bazı açıklamalar için bk. Celâl Yeniçeri, s. 110-115). Gök kelimesinin Kur’an’daki kullanımları dikkate alınarak genişletilen şey, bu ve benzeri bağlamlarda “evren” (Esed, III, 1070-1071), “dünyanın dışındaki bütün kâinat” (Celal Kırca, s. 62) anlamlarında yorumlanabilmektedir. Râzî göğün binaya ve yerin döşeğe benzetilmesini, göğün ana yapısında değişme olmamasına, yerin ise genişleme-daralma, denizlerinin  karaya dönüşmesi gibi değişkenliklere açık olmasına bağlar (XXVIII, 225-226; göklerin ve yerin  yaratılması hakkında  bk. Bakara 2/22, 29).  Müfessirler “her şeyden çift çift yaratma”nın anlamını açıklarken daha çok “gece-gündüz, erkek-dişi, yer-gök, insan-cin, iman-küfür, ay-güneş” gibi karşıtlık örnekleri üzerinde durmuşlardır. Taberî bunu “Cenâb-ı Allah’ın her yarattığının yanı sıra amaç ve işlevi itibariyle ondan farklı bir ikincisini yaratması” şeklinde anlamanın uygun olacağı kanaatindedir. Yine Taberî’nin izahına göre burada esas amaç Allah’ın yaratma sıfatına dikkat çekmektir.  O’nun yaratmasını –meselâ ateşin yakma özelliği gibi– tek sonuçlu olarak algılamamak gerekir, O dilediği her şeyi dilediği biçimde yaratma gücüne sahiptir  (XXVII, 8-9). Elmalılı, bu konudaki görüşleri özetledikten sonra, Beyzâvî’nin “her cinsten iki nevi bulunduğu” tarzındaki yorumunu öncekileri  de içine alması itibariyle daha kapsamlı bulur. Bununla birlikte o, âyetteki “her şey” ifadesinin sadece cinsleri değil fertleri de kapsadığını dikkate alarak, burada dış âlemdekiler ile onların zihindeki formlarının uyumlu eşleşmesiyle tecelli eden idrak olayına da işaret bulunduğu yorumunu yapar; herhangi bir şey hakkında meydana gelen şuur hâdisesinde bu ikiliğin kaçınılmaz olduğunu, bu ikilik içinde birleştirilmeden hiçbir şeyin tasdik edilemeyeceğini, tefekkür ve tezekkürde bulunulamayacağını, âyetin sonunda yer alan “ki inceden inceye düşünesiniz” ifadesinin de bunu desteklediğini belirtir (bk. VI, 4543-4544; ayrıca bk. Yâsîn 36/36). 49. âyetin son cümlesi hem bu âyette hem de önceki iki âyette belirtilenler üzerinde düşünülmesini kapsadığından (Zemahşerî, IV, 31), sırf bulunduğu âyete bağlı düşünülmemesi için meâlinde bu cümleyi “İnceden inceye düşünesiniz diye!” şeklinde sona aldık."
  },
  {
    "surahNo": 51,
    "ayahID": 51,
    "tefsirText": "İlk üç âyette Cenâb-ı Allah’ın  sonsuz kudretini gösteren ve her an yakın çevremizde gözlemleyebildiğimiz üç çeşit kanıta değinilmekte, 50-51. âyetlerde de bunlardan  çıkarılması gereken sonuç peygamberinin dilinden bir uyarı tarzında ifade edilmektedir: Başka kaçacak, sığınılacak yer yoktur, yalnız Allah’a sığınmak, O’nun gösterdiği yolda yürümek gerekir; O’nun yanında başka tanrılar uydurmak akıl ve iz‘an sahibi varlıklara yaraşmaz.  47. âyette geçen eyd kelimesinin “kuvvet, kudret” veya “eller” mânalarına göre değişik yorumlar yapılmıştır; bu yorumlar, göğün muhteşem yapısı ve düzeninin  yüce Allah’ın kudretine  bağlı olduğunu ifade etme noktasında birleşir (Râzî, XXVIII,  226). “Şüphesiz biz genişletmekteyiz” diye çevrilen cümle için yapılan başlıca yorumlar şunlardır: a) Biz vüs’at yani genişlik ve kudret sahibiyiz; semadaki bu ihtişamı sağlamakla kudretimizden bir şey eksildiği sanılmamalıdır, dilesek daha da genişletiriz. Bakara sûresinin  255 ve Kaf sûresinin 38. âyetlerindeki içerik ve üslûp bu mânayı çağrıştırmaktadır. b) Hiçbir şeye muhtaç olmadığımız gibi nimetleri bol bol ihsan eden de biziz; sıkıntıları giderir, darda kalanlara genişlik veririz (Şevkânî, V, 105; Elmalılı, VI, 4542-4543). c) Evreni genişletmekteyiz. Bu yorum  daha çok, uzay cisimlerinin birbirinden uzaklaştığı ve aralarındaki mesafenin gitgide arttığı yönündeki bilimsel tesbitten hareketle ortaya konan “genişleme teorisi” ışığında yapılmıştır (bk. Celal Kırca, s. 62-63; eski dönemlerin âlimlerinden  bu yorumu destekleyen bazı açıklamalar için bk. Celâl Yeniçeri, s. 110-115). Gök kelimesinin Kur’an’daki kullanımları dikkate alınarak genişletilen şey, bu ve benzeri bağlamlarda “evren” (Esed, III, 1070-1071), “dünyanın dışındaki bütün kâinat” (Celal Kırca, s. 62) anlamlarında yorumlanabilmektedir. Râzî göğün binaya ve yerin döşeğe benzetilmesini, göğün ana yapısında değişme olmamasına, yerin ise genişleme-daralma, denizlerinin  karaya dönüşmesi gibi değişkenliklere açık olmasına bağlar (XXVIII, 225-226; göklerin ve yerin  yaratılması hakkında  bk. Bakara 2/22, 29).  Müfessirler “her şeyden çift çift yaratma”nın anlamını açıklarken daha çok “gece-gündüz, erkek-dişi, yer-gök, insan-cin, iman-küfür, ay-güneş” gibi karşıtlık örnekleri üzerinde durmuşlardır. Taberî bunu “Cenâb-ı Allah’ın her yarattığının yanı sıra amaç ve işlevi itibariyle ondan farklı bir ikincisini yaratması” şeklinde anlamanın uygun olacağı kanaatindedir. Yine Taberî’nin izahına göre burada esas amaç Allah’ın yaratma sıfatına dikkat çekmektir.  O’nun yaratmasını –meselâ ateşin yakma özelliği gibi– tek sonuçlu olarak algılamamak gerekir, O dilediği her şeyi dilediği biçimde yaratma gücüne sahiptir  (XXVII, 8-9). Elmalılı, bu konudaki görüşleri özetledikten sonra, Beyzâvî’nin “her cinsten iki nevi bulunduğu” tarzındaki yorumunu öncekileri  de içine alması itibariyle daha kapsamlı bulur. Bununla birlikte o, âyetteki “her şey” ifadesinin sadece cinsleri değil fertleri de kapsadığını dikkate alarak, burada dış âlemdekiler ile onların zihindeki formlarının uyumlu eşleşmesiyle tecelli eden idrak olayına da işaret bulunduğu yorumunu yapar; herhangi bir şey hakkında meydana gelen şuur hâdisesinde bu ikiliğin kaçınılmaz olduğunu, bu ikilik içinde birleştirilmeden hiçbir şeyin tasdik edilemeyeceğini, tefekkür ve tezekkürde bulunulamayacağını, âyetin sonunda yer alan “ki inceden inceye düşünesiniz” ifadesinin de bunu desteklediğini belirtir (bk. VI, 4543-4544; ayrıca bk. Yâsîn 36/36). 49. âyetin son cümlesi hem bu âyette hem de önceki iki âyette belirtilenler üzerinde düşünülmesini kapsadığından (Zemahşerî, IV, 31), sırf bulunduğu âyete bağlı düşünülmemesi için meâlinde bu cümleyi “İnceden inceye düşünesiniz diye!” şeklinde sona aldık."
  }
]